gauthsdk/__init__.py
gauthsdk/auth.py
gauthsdk/client.py
gauthsdk/endpoints.py
gauthsdk/errors.py
gauthsdk/models.py
gauthsdk/users.py
gauthsdk-0.3.0.dist-info/METADATA
gauthsdk-0.3.0.dist-info/WHEEL
gauthsdk-0.3.0.dist-info/top_level.txt
gauthsdk-0.3.0.dist-info/RECORD
