Metadata-Version: 2.4
Name: gauthsdk
Version: 0.3.0
Summary: Python SDK for GAuth API - GearVN Authentication Service
Author-email: GearVN <dev@gearvn.com>
License: MIT
Project-URL: Homepage, https://github.com/gearvn/gvn-auth
Project-URL: Documentation, https://github.com/gearvn/gvn-auth#readme
Project-URL: Repository, https://github.com/gearvn/gvn-auth
Keywords: gauth,authentication,sdk,api
Classifier: Development Status :: 4 - Beta
Classifier: Intended Audience :: Developers
Classifier: License :: OSI Approved :: MIT License
Classifier: Operating System :: OS Independent
Classifier: Programming Language :: Python :: 3
Classifier: Programming Language :: Python :: 3.8
Classifier: Programming Language :: Python :: 3.9
Classifier: Programming Language :: Python :: 3.10
Classifier: Programming Language :: Python :: 3.11
Classifier: Programming Language :: Python :: 3.12
Classifier: Topic :: Software Development :: Libraries :: Python Modules
Requires-Python: >=3.8
Requires-Dist: requests>=2.25.0
Provides-Extra: dev
Requires-Dist: pytest>=7.0.0; extra == "dev"
Requires-Dist: pytest-cov>=4.0.0; extra == "dev"
Requires-Dist: black>=23.0.0; extra == "dev"
Requires-Dist: mypy>=1.0.0; extra == "dev"
Requires-Dist: ruff>=0.1.0; extra == "dev"
